{
  "system_status": "active",
  "currency": "USD",
  "products": [
    {
      "id": "CREATOR-001",
      "name": "The Viral Hook Database",
      "price": 29,
      "description": "A titanium-grade asset for the creator sector. Optimized for high-performance workflows.",
      "tags": [
        "CREATOR",
        "TITANIUM"
      ],
      "stripe_link": null,
      "download_file": "creator_001.zip",
      "visual": "GLASS_UI",
      "theme": {
        "accent": "#ff2a2a"
      },
      "spatial": {
        "tilt": true,
        "distortion": true
      }
    },
    {
      "id": "CREATOR-002",
      "name": "OBS Commander",
      "price": 39,
      "description": "A titanium-grade asset for the creator sector. Optimized for high-performance workflows.",
      "tags": [
        "CREATOR",
        "TITANIUM"
      ],
      "stripe_link": null,
      "download_file": "creator_002.zip",
      "visual": "GLASS_UI",
      "theme": {
        "accent": "#ff2a2a"
      },
      "spatial": {
        "tilt": true,
        "distortion": true
      }
    },
    {
      "id": "CREATOR-003",
      "name": "The Content OS",
      "price": 49,
      "description": "A titanium-grade asset for the creator sector. Optimized for high-performance workflows.",
      "tags": [
        "CREATOR",
        "TITANIUM"
      ],
      "stripe_link": null,
      "download_file": "creator_003.zip",
      "visual": "GLASS_UI",
      "theme": {
        "accent": "#ff2a2a"
      },
      "spatial": {
        "tilt": true,
        "distortion": true
      }
    },
    {
      "id": "CREATOR-004",
      "name": "Titanium LUTs",
      "price": 59,
      "description": "A titanium-grade asset for the creator sector. Optimized for high-performance workflows.",
      "tags": [
        "CREATOR",
        "TITANIUM"
      ],
      "stripe_link": null,
      "download_file": "creator_004.zip",
      "visual": "GLASS_UI",
      "theme": {
        "accent": "#ff2a2a"
      },
      "spatial": {
        "tilt": true,
        "distortion": true
      }
    },
    {
      "id": "CREATOR-005",
      "name": "The Soundscape",
      "price": 69,
      "description": "A titanium-grade asset for the creator sector. Optimized for high-performance workflows.",
      "tags": [
        "CREATOR",
        "TITANIUM"
      ],
      "stripe_link": null,
      "download_file": "creator_005.zip",
      "visual": "GLASS_UI",
      "theme": {
        "accent": "#ff2a2a"
      },
      "spatial": {
        "tilt": true,
        "distortion": true
      }
    },
    {
      "id": "CREATOR-006",
      "name": "Thumbnail Architect",
      "price": 79,
      "description": "A titanium-grade asset for the creator sector. Optimized for high-performance workflows.",
      "tags": [
        "CREATOR",
        "TITANIUM"
      ],
      "stripe_link": null,
      "download_file": "creator_006.zip",
      "visual": "GLASS_UI",
      "theme": {
        "accent": "#ff2a2a"
      },
      "spatial": {
        "tilt": true,
        "distortion": true
      }
    },
    {
      "id": "CREATOR-007",
      "name": "Discord Empire",
      "price": 89,
      "description": "A titanium-grade asset for the creator sector. Optimized for high-performance workflows.",
      "tags": [
        "CREATOR",
        "TITANIUM"
      ],
      "stripe_link": null,
      "download_file": "creator_007.zip",
      "visual": "GLASS_UI",
      "theme": {
        "accent": "#ff2a2a"
      },
      "spatial": {
        "tilt": true,
        "distortion": true
      }
    },
    {
      "id": "PRO-001",
      "name": "The Sentinel Protocol",
      "price": 29,
      "description": "A titanium-grade asset for the pro sector. Optimized for high-performance workflows.",
      "tags": [
        "PRO",
        "TITANIUM"
      ],
      "stripe_link": null,
      "download_file": "pro_001.zip",
      "visual": "SENTINEL",
      "theme": {
        "accent": "#0088ff"
      },
      "spatial": {
        "tilt": true,
        "distortion": true
      }
    },
    {
      "id": "PRO-002",
      "name": "The Regex God",
      "price": 39,
      "description": "A titanium-grade asset for the pro sector. Optimized for high-performance workflows.",
      "tags": [
        "PRO",
        "TITANIUM"
      ],
      "stripe_link": null,
      "download_file": "pro_002.zip",
      "visual": "SENTINEL",
      "theme": {
        "accent": "#0088ff"
      },
      "spatial": {
        "tilt": true,
        "distortion": true
      }
    },
    {
      "id": "PRO-003",
      "name": "Bash Automation Suite",
      "price": 49,
      "description": "A titanium-grade asset for the pro sector. Optimized for high-performance workflows.",
      "tags": [
        "PRO",
        "TITANIUM"
      ],
      "stripe_link": null,
      "download_file": "pro_003.zip",
      "visual": "SENTINEL",
      "theme": {
        "accent": "#0088ff"
      },
      "spatial": {
        "tilt": true,
        "distortion": true
      }
    },
    {
      "id": "PRO-004",
      "name": "Docker Fortress",
      "price": 59,
      "description": "A titanium-grade asset for the pro sector. Optimized for high-performance workflows.",
      "tags": [
        "PRO",
        "TITANIUM"
      ],
      "stripe_link": null,
      "download_file": "pro_004.zip",
      "visual": "SENTINEL",
      "theme": {
        "accent": "#0088ff"
      },
      "spatial": {
        "tilt": true,
        "distortion": true
      }
    },
    {
      "id": "PRO-005",
      "name": "API Wrapper Kit",
      "price": 69,
      "description": "A titanium-grade asset for the pro sector. Optimized for high-performance workflows.",
      "tags": [
        "PRO",
        "TITANIUM"
      ],
      "stripe_link": null,
      "download_file": "pro_005.zip",
      "visual": "SENTINEL",
      "theme": {
        "accent": "#0088ff"
      },
      "spatial": {
        "tilt": true,
        "distortion": true
      }
    },
    {
      "id": "PRO-006",
      "name": "Git Hook Armory",
      "price": 79,
      "description": "A titanium-grade asset for the pro sector. Optimized for high-performance workflows.",
      "tags": [
        "PRO",
        "TITANIUM"
      ],
      "stripe_link": null,
      "download_file": "pro_006.zip",
      "visual": "SENTINEL",
      "theme": {
        "accent": "#0088ff"
      },
      "spatial": {
        "tilt": true,
        "distortion": true
      }
    },
    {
      "id": "PRO-007",
      "name": "The Code Vault",
      "price": 89,
      "description": "A titanium-grade asset for the pro sector. Optimized for high-performance workflows.",
      "tags": [
        "PRO",
        "TITANIUM"
      ],
      "stripe_link": null,
      "download_file": "pro_007.zip",
      "visual": "SENTINEL",
      "theme": {
        "accent": "#0088ff"
      },
      "spatial": {
        "tilt": true,
        "distortion": true
      }
    },
    {
      "id": "VISUALS-001",
      "name": "Glass UI: Titan Edition",
      "price": 29,
      "description": "A titanium-grade asset for the visuals sector. Optimized for high-performance workflows.",
      "tags": [
        "VISUALS",
        "TITANIUM"
      ],
      "stripe_link": null,
      "download_file": "visuals_001.zip",
      "visual": "GLASS_UI",
      "theme": {
        "accent": "#bc13fe"
      },
      "spatial": {
        "tilt": true,
        "distortion": true
      }
    },
    {
      "id": "VISUALS-002",
      "name": "Neon Typography",
      "price": 39,
      "description": "A titanium-grade asset for the visuals sector. Optimized for high-performance workflows.",
      "tags": [
        "VISUALS",
        "TITANIUM"
      ],
      "stripe_link": null,
      "download_file": "visuals_002.zip",
      "visual": "GLASS_UI",
      "theme": {
        "accent": "#bc13fe"
      },
      "spatial": {
        "tilt": true,
        "distortion": true
      }
    },
    {
      "id": "VISUALS-003",
      "name": "Prism Shaders",
      "price": 49,
      "description": "A titanium-grade asset for the visuals sector. Optimized for high-performance workflows.",
      "tags": [
        "VISUALS",
        "TITANIUM"
      ],
      "stripe_link": null,
      "download_file": "visuals_003.zip",
      "visual": "GLASS_UI",
      "theme": {
        "accent": "#bc13fe"
      },
      "spatial": {
        "tilt": true,
        "distortion": true
      }
    },
    {
      "id": "VISUALS-004",
      "name": "Cyberpunk Icon Pack",
      "price": 59,
      "description": "A titanium-grade asset for the visuals sector. Optimized for high-performance workflows.",
      "tags": [
        "VISUALS",
        "TITANIUM"
      ],
      "stripe_link": null,
      "download_file": "visuals_004.zip",
      "visual": "GLASS_UI",
      "theme": {
        "accent": "#bc13fe"
      },
      "spatial": {
        "tilt": true,
        "distortion": true
      }
    },
    {
      "id": "VISUALS-005",
      "name": "The Grid System",
      "price": 69,
      "description": "A titanium-grade asset for the visuals sector. Optimized for high-performance workflows.",
      "tags": [
        "VISUALS",
        "TITANIUM"
      ],
      "stripe_link": null,
      "download_file": "visuals_005.zip",
      "visual": "GLASS_UI",
      "theme": {
        "accent": "#bc13fe"
      },
      "spatial": {
        "tilt": true,
        "distortion": true
      }
    },
    {
      "id": "VISUALS-006",
      "name": "Motion UI Kit",
      "price": 79,
      "description": "A titanium-grade asset for the visuals sector. Optimized for high-performance workflows.",
      "tags": [
        "VISUALS",
        "TITANIUM"
      ],
      "stripe_link": null,
      "download_file": "visuals_006.zip",
      "visual": "GLASS_UI",
      "theme": {
        "accent": "#bc13fe"
      },
      "spatial": {
        "tilt": true,
        "distortion": true
      }
    },
    {
      "id": "VISUALS-007",
      "name": "Figma Wireframe Kit",
      "price": 89,
      "description": "A titanium-grade asset for the visuals sector. Optimized for high-performance workflows.",
      "tags": [
        "VISUALS",
        "TITANIUM"
      ],
      "stripe_link": null,
      "download_file": "visuals_007.zip",
      "visual": "GLASS_UI",
      "theme": {
        "accent": "#bc13fe"
      },
      "spatial": {
        "tilt": true,
        "distortion": true
      }
    },
    {
      "id": "ENTREPRENEUR-001",
      "name": "The Pitch Deck",
      "price": 29,
      "description": "A titanium-grade asset for the entrepreneur sector. Optimized for high-performance workflows.",
      "tags": [
        "ENTREPRENEUR",
        "TITANIUM"
      ],
      "stripe_link": null,
      "download_file": "entrepreneur_001.zip",
      "visual": "GLASS_UI",
      "theme": {
        "accent": "#ffb300"
      },
      "spatial": {
        "tilt": true,
        "distortion": true
      }
    },
    {
      "id": "ENTREPRENEUR-002",
      "name": "Niche Hunter",
      "price": 39,
      "description": "A titanium-grade asset for the entrepreneur sector. Optimized for high-performance workflows.",
      "tags": [
        "ENTREPRENEUR",
        "TITANIUM"
      ],
      "stripe_link": null,
      "download_file": "entrepreneur_002.zip",
      "visual": "GLASS_UI",
      "theme": {
        "accent": "#ffb300"
      },
      "spatial": {
        "tilt": true,
        "distortion": true
      }
    },
    {
      "id": "ENTREPRENEUR-003",
      "name": "The Operating Agreement",
      "price": 49,
      "description": "A titanium-grade asset for the entrepreneur sector. Optimized for high-performance workflows.",
      "tags": [
        "ENTREPRENEUR",
        "TITANIUM"
      ],
      "stripe_link": null,
      "download_file": "entrepreneur_003.zip",
      "visual": "GLASS_UI",
      "theme": {
        "accent": "#ffb300"
      },
      "spatial": {
        "tilt": true,
        "distortion": true
      }
    },
    {
      "id": "ENTREPRENEUR-004",
      "name": "Cold Email Warfare",
      "price": 59,
      "description": "A titanium-grade asset for the entrepreneur sector. Optimized for high-performance workflows.",
      "tags": [
        "ENTREPRENEUR",
        "TITANIUM"
      ],
      "stripe_link": null,
      "download_file": "entrepreneur_004.zip",
      "visual": "GLASS_UI",
      "theme": {
        "accent": "#ffb300"
      },
      "spatial": {
        "tilt": true,
        "distortion": true
      }
    },
    {
      "id": "ENTREPRENEUR-005",
      "name": "The Financial Model",
      "price": 69,
      "description": "A titanium-grade asset for the entrepreneur sector. Optimized for high-performance workflows.",
      "tags": [
        "ENTREPRENEUR",
        "TITANIUM"
      ],
      "stripe_link": null,
      "download_file": "entrepreneur_005.zip",
      "visual": "GLASS_UI",
      "theme": {
        "accent": "#ffb300"
      },
      "spatial": {
        "tilt": true,
        "distortion": true
      }
    },
    {
      "id": "ENTREPRENEUR-006",
      "name": "MVP Checklist",
      "price": 79,
      "description": "A titanium-grade asset for the entrepreneur sector. Optimized for high-performance workflows.",
      "tags": [
        "ENTREPRENEUR",
        "TITANIUM"
      ],
      "stripe_link": null,
      "download_file": "entrepreneur_006.zip",
      "visual": "GLASS_UI",
      "theme": {
        "accent": "#ffb300"
      },
      "spatial": {
        "tilt": true,
        "distortion": true
      }
    },
    {
      "id": "ENTREPRENEUR-007",
      "name": "Idea Vault",
      "price": 89,
      "description": "A titanium-grade asset for the entrepreneur sector. Optimized for high-performance workflows.",
      "tags": [
        "ENTREPRENEUR",
        "TITANIUM"
      ],
      "stripe_link": null,
      "download_file": "entrepreneur_007.zip",
      "visual": "GLASS_UI",
      "theme": {
        "accent": "#ffb300"
      },
      "spatial": {
        "tilt": true,
        "distortion": true
      }
    },
    {
      "id": "BUSINESS-001",
      "name": "The Scaling OS",
      "price": 29,
      "description": "A titanium-grade asset for the business sector. Optimized for high-performance workflows.",
      "tags": [
        "BUSINESS",
        "TITANIUM"
      ],
      "stripe_link": null,
      "download_file": "business_001.zip",
      "visual": "GLASS_UI",
      "theme": {
        "accent": "#00d9ff"
      },
      "spatial": {
        "tilt": true,
        "distortion": true
      }
    },
    {
      "id": "BUSINESS-002",
      "name": "Hiring Protocol",
      "price": 39,
      "description": "A titanium-grade asset for the business sector. Optimized for high-performance workflows.",
      "tags": [
        "BUSINESS",
        "TITANIUM"
      ],
      "stripe_link": null,
      "download_file": "business_002.zip",
      "visual": "GLASS_UI",
      "theme": {
        "accent": "#00d9ff"
      },
      "spatial": {
        "tilt": true,
        "distortion": true
      }
    },
    {
      "id": "BUSINESS-003",
      "name": "Inventory Tracker",
      "price": 49,
      "description": "A titanium-grade asset for the business sector. Optimized for high-performance workflows.",
      "tags": [
        "BUSINESS",
        "TITANIUM"
      ],
      "stripe_link": null,
      "download_file": "business_003.zip",
      "visual": "GLASS_UI",
      "theme": {
        "accent": "#00d9ff"
      },
      "spatial": {
        "tilt": true,
        "distortion": true
      }
    },
    {
      "id": "BUSINESS-004",
      "name": "CRM Lite",
      "price": 59,
      "description": "A titanium-grade asset for the business sector. Optimized for high-performance workflows.",
      "tags": [
        "BUSINESS",
        "TITANIUM"
      ],
      "stripe_link": null,
      "download_file": "business_004.zip",
      "visual": "GLASS_UI",
      "theme": {
        "accent": "#00d9ff"
      },
      "spatial": {
        "tilt": true,
        "distortion": true
      }
    },
    {
      "id": "BUSINESS-005",
      "name": "Social Media Calendar",
      "price": 69,
      "description": "A titanium-grade asset for the business sector. Optimized for high-performance workflows.",
      "tags": [
        "BUSINESS",
        "TITANIUM"
      ],
      "stripe_link": null,
      "download_file": "business_005.zip",
      "visual": "GLASS_UI",
      "theme": {
        "accent": "#00d9ff"
      },
      "spatial": {
        "tilt": true,
        "distortion": true
      }
    },
    {
      "id": "BUSINESS-006",
      "name": "Onboarding Engine",
      "price": 79,
      "description": "A titanium-grade asset for the business sector. Optimized for high-performance workflows.",
      "tags": [
        "BUSINESS",
        "TITANIUM"
      ],
      "stripe_link": null,
      "download_file": "business_006.zip",
      "visual": "GLASS_UI",
      "theme": {
        "accent": "#00d9ff"
      },
      "spatial": {
        "tilt": true,
        "distortion": true
      }
    },
    {
      "id": "BUSINESS-007",
      "name": "Compliance Shield",
      "price": 89,
      "description": "A titanium-grade asset for the business sector. Optimized for high-performance workflows.",
      "tags": [
        "BUSINESS",
        "TITANIUM"
      ],
      "stripe_link": null,
      "download_file": "business_007.zip",
      "visual": "GLASS_UI",
      "theme": {
        "accent": "#00d9ff"
      },
      "spatial": {
        "tilt": true,
        "distortion": true
      }
    },
    {
      "id": "ENTERPRISE-001",
      "name": "Disaster Recovery Plan",
      "price": 29,
      "description": "A titanium-grade asset for the enterprise sector. Optimized for high-performance workflows.",
      "tags": [
        "ENTERPRISE",
        "TITANIUM"
      ],
      "stripe_link": null,
      "download_file": "enterprise_001.zip",
      "visual": "WEBGPU",
      "theme": {
        "accent": "#ffffff"
      },
      "spatial": {
        "tilt": true,
        "distortion": true
      }
    },
    {
      "id": "ENTERPRISE-002",
      "name": "Cloud Architecture Patterns",
      "price": 39,
      "description": "A titanium-grade asset for the enterprise sector. Optimized for high-performance workflows.",
      "tags": [
        "ENTERPRISE",
        "TITANIUM"
      ],
      "stripe_link": null,
      "download_file": "enterprise_002.zip",
      "visual": "WEBGPU",
      "theme": {
        "accent": "#ffffff"
      },
      "spatial": {
        "tilt": true,
        "distortion": true
      }
    },
    {
      "id": "ENTERPRISE-003",
      "name": "Data Governance Framework",
      "price": 49,
      "description": "A titanium-grade asset for the enterprise sector. Optimized for high-performance workflows.",
      "tags": [
        "ENTERPRISE",
        "TITANIUM"
      ],
      "stripe_link": null,
      "download_file": "enterprise_003.zip",
      "visual": "WEBGPU",
      "theme": {
        "accent": "#ffffff"
      },
      "spatial": {
        "tilt": true,
        "distortion": true
      }
    },
    {
      "id": "ENTERPRISE-004",
      "name": "Incident Response Playbook",
      "price": 59,
      "description": "A titanium-grade asset for the enterprise sector. Optimized for high-performance workflows.",
      "tags": [
        "ENTERPRISE",
        "TITANIUM"
      ],
      "stripe_link": null,
      "download_file": "enterprise_004.zip",
      "visual": "WEBGPU",
      "theme": {
        "accent": "#ffffff"
      },
      "spatial": {
        "tilt": true,
        "distortion": true
      }
    },
    {
      "id": "ENTERPRISE-005",
      "name": "Load Balancer Configs",
      "price": 69,
      "description": "A titanium-grade asset for the enterprise sector. Optimized for high-performance workflows.",
      "tags": [
        "ENTERPRISE",
        "TITANIUM"
      ],
      "stripe_link": null,
      "download_file": "enterprise_005.zip",
      "visual": "WEBGPU",
      "theme": {
        "accent": "#ffffff"
      },
      "spatial": {
        "tilt": true,
        "distortion": true
      }
    },
    {
      "id": "ENTERPRISE-006",
      "name": "Microservices Blueprint",
      "price": 79,
      "description": "A titanium-grade asset for the enterprise sector. Optimized for high-performance workflows.",
      "tags": [
        "ENTERPRISE",
        "TITANIUM"
      ],
      "stripe_link": null,
      "download_file": "enterprise_006.zip",
      "visual": "WEBGPU",
      "theme": {
        "accent": "#ffffff"
      },
      "spatial": {
        "tilt": true,
        "distortion": true
      }
    },
    {
      "id": "ENTERPRISE-007",
      "name": "Legacy Migration Protocol",
      "price": 89,
      "description": "A titanium-grade asset for the enterprise sector. Optimized for high-performance workflows.",
      "tags": [
        "ENTERPRISE",
        "TITANIUM"
      ],
      "stripe_link": null,
      "download_file": "enterprise_007.zip",
      "visual": "WEBGPU",
      "theme": {
        "accent": "#ffffff"
      },
      "spatial": {
        "tilt": true,
        "distortion": true
      }
    }
  ]
}